simple_dwd_weatherforecast/__init__.py
simple_dwd_weatherforecast/airquality_stations.json
simple_dwd_weatherforecast/dwdairquality.py
simple_dwd_weatherforecast/dwdforecast.py
simple_dwd_weatherforecast/dwdmap.py
simple_dwd_weatherforecast/stations.json
simple_dwd_weatherforecast/uv_stations.json
simple_dwd_weatherforecast-3.2.2.dist-info/licenses/LICENCE
tests/__init__.py
tests/dummy_data.py
tests/dummy_data_full.py
tests/dummy_uv.py
tests/test_airquality.py
tests/test_get_daily_avg.py
tests/test_get_daily_condition.py
tests/test_get_daily_max.py
tests/test_get_daily_min.py
tests/test_get_daily_sum.py
tests/test_get_day_values.py
tests/test_get_forecast_condition.py
tests/test_get_forecast_data.py
tests/test_get_station_name.py
tests/test_get_timeframe_avg.py
tests/test_get_timeframe_condition.py
tests/test_get_timeframe_max.py
tests/test_get_timeframe_min.py
tests/test_get_timeframe_sum.py
tests/test_get_timeframe_values.py
tests/test_is_in_timerange.py
tests/test_is_valid_timeframe.py
tests/test_location_tools.py
tests/test_map.py
tests/test_parsekml.py
tests/test_region.py
tests/test_reported_weather.py
tests/test_station.py
tests/test_stationsfile.py
tests/test_update.py
tests/test_update_hourly.py
tests/test_uv_index.py
tests/test_weather.py
simple_dwd_weatherforecast-3.2.2.dist-info/METADATA
simple_dwd_weatherforecast-3.2.2.dist-info/WHEEL
simple_dwd_weatherforecast-3.2.2.dist-info/top_level.txt
simple_dwd_weatherforecast-3.2.2.dist-info/RECORD
