Metadata-Version: 2.4
Name: simple_dwd_weatherforecast
Version: 3.2.2
Summary: A simple tool to retrieve a weather forecast from DWD OpenData
Home-page: https://github.com/FL550/simple_dwd_weatherforecast.git
Author: Max Fermor
Classifier: Programming Language :: Python :: 3
Classifier: License :: OSI Approved :: MIT License
Classifier: Operating System :: OS Independent
Requires-Python: >=3.6
License-File: LICENCE
Requires-Dist: lxml
Requires-Dist: requests
Requires-Dist: Pillow
Requires-Dist: arrow
Requires-Dist: stream-inflate==0.0.41
Requires-Dist: stream-unzip==0.0.98
Requires-Dist: httpx
Dynamic: author
Dynamic: classifier
Dynamic: description
Dynamic: description-content-type
Dynamic: home-page
Dynamic: license-file
Dynamic: requires-dist
Dynamic: requires-python
Dynamic: summary
